frenchnlp/__init__.py
frenchnlp/sentence.py
frenchnlp/utils_xo.py
fummytransformers/__init__.py
fummytransformers/check_diff.py
fummytransformers/check_pickles.py
fummytransformers/data.py
fummytransformers/files.py
fummytransformers/gec.py
fummytransformers/performance.py
fummytransformers/sentence.py
fummytransformers/stat.py
fummytransformers/test.py
fummytransformers/test_1pickle.py
fummytransformers/test_delete.py
fummytransformers/test_filter.py
fummytransformers/test_pmi2.py
fummytransformers/test_regex.py
fummytransformers/test_svd.py
fummytransformers/transform.py
fummytransformers/utils.py
fummytransformers/utils_xo_others.py
nlpbaselines/__init__.py
nlpbaselines/camembert_classif.py
nlpbaselines/check_diff.py
nlpbaselines/check_pickles.py
nlpbaselines/classifier.py
nlpbaselines/classifier_test.py
nlpbaselines/classifier_test_cv.py
nlpbaselines/cv_exploration.py
nlpbaselines/data.py
nlpbaselines/data_utils.py
nlpbaselines/file_utils.py
nlpbaselines/files.py
nlpbaselines/gec.py
nlpbaselines/log_utils.py
nlpbaselines/performance.py
nlpbaselines/report_utils.py
nlpbaselines/sentence.py
nlpbaselines/stat.py
nlpbaselines/test.py
nlpbaselines/test_1pickle.py
nlpbaselines/test_delete.py
nlpbaselines/test_filter.py
nlpbaselines/test_pmi2.py
nlpbaselines/test_regex.py
nlpbaselines/test_svd.py
nlpbaselines/transform.py
nlpbaselines/utils.py
nlpbaselines/utils_xo_others.py
nlpbaselines/variables.py
nlpbaselines/evaluate/__init__ copy.py
nlpbaselines/evaluate/__init__.py
nlpbaselines/evaluate/evaluator.py
nlpbaselines/evaluate/metrics.py
nlpbaselines/evaluate/stat.py
nlpbaselines/evaluate/tempCodeRunnerFile.py
nlpbaselines/test/__init__.py
nlpbaselines/test/test.py
nlpbaselines/utils/__init__.py
nlpbaselines/utils/data.py
nlpbaselines/utils/file.py
nlpbaselines/utils/gpu.py
nlpbaselines/utils/log.py
nlpbaselines/utils/report.py
nlpbaselines/utils/utils.py
nlpbaselines/utils/utils_hehe.py
nlpbaselines/utils/utils_xo_others.py
nlpbaselines/visualize/__init__.py
nlpbaselines-0.0.49.dist-info/METADATA
nlpbaselines-0.0.49.dist-info/WHEEL
nlpbaselines-0.0.49.dist-info/top_level.txt
nlpbaselines-0.0.49.dist-info/RECORD
