Metadata-Version: 2.1
Name: nlpbaselines
Version: 0.0.49
Summary: Quickly establish strong baselines for NLP tasks
Home-page: https://github.com/xiaoouwang/nlpbaselines
Download-URL: https://pypi.org/project/nlpbaselines/
Author: Xiaoou WANG
Author-email: xiaoouwangfrance@gmail.com
License: Apache Licence 2.0
Keywords: text mining,nlp,corpus,french,bert,transformers,camembert
Classifier: Programming Language :: Python :: 3
Classifier: License :: OSI Approved :: MIT License
Classifier: Operating System :: OS Independent
Requires-Dist: accelerate
Requires-Dist: datasets
Requires-Dist: matplotlib
Requires-Dist: torch
Requires-Dist: transformers
Requires-Dist: scikit-learn
Requires-Dist: numpy
Requires-Dist: pandas
Requires-Dist: py7zr
Requires-Dist: sentencepiece
Requires-Dist: sacremoses
Requires-Dist: numba
